Paquete.v
//couenter
module counter #(parameter N=12)
		(input logic clk,
		 input logic reset,
		 input logic load,
		 input logic enabled,
		 input [11:0] d,
		 output logic [N-1:0]q);

always@(posedge clk, posedge reset)
	if(reset)
		q<=0;
	else if (load)
		q<=d;
	else if (enabled && !load)
		q<=q+1;

endmodule

//ROM
module memoria_ROM (input wire [11:0]addres, output wire [7:0]data);

	reg [7:0]mem[0:4095];

initial begin
	$readmemb("memoria.list",mem);
end

assign data = mem[addres];

endmodule


//f.f.D
module fetch(input clk, input reset,
	     input ena,
	     input [7:0]d,
	     output reg [3:0]instruccion,
	     output reg [3:0]operando);


	always @ (posedge clk, posedge reset)begin

		if (reset)
			begin
				operando <= 4'b0;
				instruccion <= 4'b0;
			end
		else if (ena)
			begin
				operando <= d[3:0];
				instruccion <= d[7:4];
			end
	end
endmodule



//preparacion de control

module preparacion(input clk, input reset,
		   input logic load_counter, input logic ena_load_counter,
		   input logic enabled_ct, input logic enabled_fetch,
		   input logic [11:0]in_dato,
		   output wire [7:0]program_byte, output wire [3:0]intsr, output wire [3:0]oprnd);


	output wire [11:0]out_counter;

	counter co1(.clk(clk), .reset(reset),
		    .load(ena_load_counter), .enabled(enabled_ct),
		    .d(in_dato),
		    .q(out_counter) );




	wire [7:0]out_ROM;

	memoria_ROM r1(.addres(out_counter), .data(out_ROM) );



	output wire [3:0]fetch_instruccions;
	output wire [3:0]fetch_operando;

	fetch ftc(.clk(clk), .reset(reset),
		  .ena(enabled_fetch),
		  .d(out_ROM),
		  .instruccion(fetch_instruccions), .operando(fetch_operando) );

assign program_byte = out_ROM;
assign intsr = fetch_instruccions;
assign oprnd = fetch_operando;


endmodule

Paquete_tb.v
module testbench();

reg clk = 0;
reg reset = 0;
reg ena_load_counter = 0;
reg loadCounter = 0;
reg enabledCounter = 0;
reg enabled_fetch = 0;
reg [11:0]dato;

output wire[7:0]Program_byte;
output wire[3:0]instruccion;
output wire[3:0]operando;



preparacion part1(clk, reset,
								  loadCounter, ena_load_counter,
									enabledCounter,  enabled_fetch,
									dato,
									Program_byte, instruccion, operando );

initial begin
	$display(" ");
	$display(" LOAD COUNTER    | Program byte  |   Instruccion   |  Operando  |");
	$display("----------------|---------------|-----------------|------------|");
	$monitor("%b               |  %b     |   %b          |    %b    |", loadCounter, Program_byte, instruccion, operando);

	reset = 1; #1 reset = 0; #1 dato = 12'b000011100000;
	#1 enabledCounter = 1;
	#1 ena_load_counter = 1; #2 ena_load_counter = 0;
	#1 enabled_fetch = 1;
	#2 reset = 1; #1 reset = 0;
	#1 dato = 12'b000000111000; #1 ena_load_counter = 1; #2 ena_load_counter = 0;
end


always@(*)begin
	#1 clk = ~clk;
end
always@(*)begin
	#1 clk = ~clk;
end
initial
	#20 $finish;

initial begin
	$dumpfile("Paquete_tb.vcd");
	$dumpvars(0, testbench);
	end
endmodule

Paquete_tb.vcd
$date
	Thu Nov 05 16:44:20 2020
$end
$version
	Icarus Verilog
$end
$timescale
	1ps
$end
$scope module testbench $end
$var wire 4 ! operando [3:0] $end
$var wire 4 " instruccion [3:0] $end
$var wire 8 # Program_byte [7:0] $end
$var reg 1 $ clk $end
$var reg 12 % dato [11:0] $end
$var reg 1 & ena_load_counter $end
$var reg 1 ' enabledCounter $end
$var reg 1 ( enabled_fetch $end
$var reg 1 ) loadCounter $end
$var reg 1 * reset $end
$scope module part1 $end
$var wire 1 $ clk $end
$var wire 1 & ena_load_counter $end
$var wire 1 ' enabled_ct $end
$var wire 1 ( enabled_fetch $end
$var wire 12 + in_dato [11:0] $end
$var wire 4 , intsr [3:0] $end
$var wire 1 ) load_counter $end
$var wire 4 - oprnd [3:0] $end
$var wire 8 . program_byte [7:0] $end
$var wire 1 * reset $end
$var wire 12 / out_counter [11:0] $end
$var wire 8 0 out_ROM [7:0] $end
$var wire 4 1 fetch_operando [3:0] $end
$var wire 4 2 fetch_instruccions [3:0] $end
$scope module co1 $end
$var wire 1 $ clk $end
$var wire 12 3 d [11:0] $end
$var wire 1 ' enabled $end
$var wire 1 & load $end
$var wire 1 * reset $end
$var reg 12 4 q [11:0] $end
$upscope $end
$scope module ftc $end
$var wire 1 $ clk $end
$var wire 1 ( ena $end
$var wire 1 * reset $end
$var wire 8 5 d [7:0] $end
$var reg 4 6 instruccion [3:0] $end
$var reg 4 7 operando [3:0] $end
$upscope $end
$scope module r1 $end
$var wire 12 8 addres [11:0] $end
$var wire 8 9 data [7:0] $end
$upscope $end
$upscope $end
$upscope $end
$enddefinitions $end
#0
$dumpvars
b0 9
b0 8
b0 7
b0 6
b0 5
b0 4
bx 3
b0 2
b0 1
b0 0
b0 /
b0 .
b0 -
b0 ,
bx +
1*
0)
0(
0'
0&
bx %
0$
b0 #
b0 "
b0 !
$end
#1
0$
0*
#2
1$
b11100000 %
b11100000 +
b11100000 3
#3
0$
1'
#4
b11100000 #
b11100000 .
b11100000 0
b11100000 5
b11100000 9
b11100000 /
b11100000 4
b11100000 8
1$
1&
#5
0$
#6
b11100001 #
b11100001 .
b11100001 0
b11100001 5
b11100001 9
b11100001 /
b11100001 4
b11100001 8
1$
0&
#7
0$
1(
#8
b1110 "
b1110 ,
b1110 2
b1110 6
b1 !
b1 -
b1 1
b1 7
b11100010 #
b11100010 .
b11100010 0
b11100010 5
b11100010 9
b11100010 /
b11100010 4
b11100010 8
1$
#9
b0 #
b0 .
b0 0
b0 5
b0 9
b0 /
b0 4
b0 8
b0 "
b0 ,
b0 2
b0 6
b0 !
b0 -
b0 1
b0 7
0$
1*
#10
b1 #
b1 .
b1 0
b1 5
b1 9
b1 /
b1 4
b1 8
1$
0*
#11
0$
b111000 %
b111000 +
b111000 3
#12
b111000 #
b111000 .
b111000 0
b111000 5
b111000 9
b111000 /
b111000 4
b111000 8
b1 !
b1 -
b1 1
b1 7
1$
1&
#13
0$
#14
b11 "
b11 ,
b11 2
b11 6
b1000 !
b1000 -
b1000 1
b1000 7
b111001 #
b111001 .
b111001 0
b111001 5
b111001 9
b111001 /
b111001 4
b111001 8
1$
0&
#15
0$
#16
b111010 #
b111010 .
b111010 0
b111010 5
b111010 9
b111010 /
b111010 4
b111010 8
b1001 !
b1001 -
b1001 1
b1001 7
1$
#17
0$
#18
b1010 !
b1010 -
b1010 1
b1010 7
b111011 #
b111011 .
b111011 0
b111011 5
b111011 9
b111011 /
b111011 4
b111011 8
1$
#19
0$
#20
b111100 #
b111100 .
b111100 0
b111100 5
b111100 9
b111100 /
b111100 4
b111100 8
b1011 !
b1011 -
b1011 1
b1011 7
1$
